{
  "id": "foundations-04-how-a-frame-travels",
  "track": "foundations",
  "title": { "en": "How a frame travels", "zh": "一帧如何穿行" },
  "estMinutes": 4,
  "prereqs": ["foundations-02-sharing-the-air"],
  "blocks": [
    { "type": "prose",
      "en": "Let's trace one message from an app to the air and back. Each layer adds what the next one needs, like nested envelopes.",
      "zh": "让我们追踪一条消息：从应用程序到空口再返回。每一层都为下一层加上所需的东西，像一层层套叠的信封。" },
    { "type": "diagram",
      "en": "sequenceDiagram\n  participant App\n  participant MAC\n  participant PHY\n  participant AP\n  App->>MAC: data (MSDU)\n  MAC->>PHY: framed bytes + addresses\n  PHY->>AP: radio symbols over the air\n  AP-->>PHY: ACK symbols\n  PHY-->>MAC: ACK\n  MAC-->>App: delivered",
      "zh": "sequenceDiagram\n  participant App as 应用\n  participant MAC\n  participant PHY as 物理层 PHY\n  participant AP\n  App->>MAC: 数据 (MSDU)\n  MAC->>PHY: 成帧字节 + 地址\n  PHY->>AP: 无线符号经由空口\n  AP-->>PHY: ACK 符号\n  PHY-->>MAC: ACK\n  MAC-->>App: 已送达" },
    { "type": "callout", "variant": "tip",
      "en": "The MAC decides who talks and writes the addresses; the PHY turns bytes into radio symbols and back. The two upcoming tracks dig into each.",
      "zh": "MAC 决定谁来发送并写入地址；PHY 把字节变成无线符号、再变回来。接下来的两个轨道将分别深入。" },
    { "type": "widget", "widget": "quiz", "params": { "questions": [
      { "q": { "en": "Which layer turns bytes into radio symbols?", "zh": "哪一层把字节变成无线符号？" },
        "options": [
          { "en": "The PHY (physical layer)", "zh": "PHY（物理层）" },
          { "en": "The app", "zh": "应用程序" },
          { "en": "The internet", "zh": "互联网" }
        ], "answer": 0 }
    ] } }
  ],
  "cites": []
}
